ordeq_numpy/__init__.py
ordeq_numpy/_version.py
ordeq_numpy/binary_array.py
ordeq_numpy/py.typed
ordeq_numpy/text_array.py
ordeq_numpy-1.0.1.dist-info/licenses/LICENSE
ordeq_numpy-1.0.1.dist-info/METADATA
ordeq_numpy-1.0.1.dist-info/WHEEL
ordeq_numpy-1.0.1.dist-info/top_level.txt
ordeq_numpy-1.0.1.dist-info/RECORD
